duo_hmac/duo_canonicalize.py
duo_hmac/duo_hmac.py
duo_hmac/duo_hmac_utils.py
duo_hmac/duo_hmac_validation.py
duo_hmac-0.1.0.dist-info/LICENSE
duo_hmac-0.1.0.dist-info/METADATA
duo_hmac-0.1.0.dist-info/WHEEL
duo_hmac-0.1.0.dist-info/top_level.txt
duo_hmac-0.1.0.dist-info/RECORD
