Metadata-Version: 2.1
Name: duo_hmac
Version: 0.1.0
Summary: An implementation of the Duo Security API authentication scheme.
Author: Duo Security
Maintainer: Duo Security
Project-URL: Repository, https://github.com/duosecurity/duo_hmac_python
Project-URL: Bug Tracker, https://github.com/duosecurity/duo_hmac_python/issues
Keywords: duo,hmac
Classifier: Development Status :: 4 - Beta
Classifier: Intended Audience :: Developers
Classifier: License :: OSI Approved :: MIT License
Classifier: Programming Language :: Python :: 3
Classifier: Programming Language :: Python :: 3.8
Classifier: Programming Language :: Python :: 3.9
Classifier: Programming Language :: Python :: 3.10
Classifier: Programming Language :: Python :: 3.11
Classifier: Topic :: Security :: Cryptography
Requires-Python: >=3.8
License-File: LICENSE
